<?xml version="1.0" encoding="UTF-8"?>
<?xml-model href="../../schemas/tagLibrary_elementDesc.rng" type="application/xml" schematypens="http://relaxng.org/ns/structure/1.0"?>
<div xmlns="http://www.tei-c.org/ns/1.0"
     xmlns:eg="http://www.tei-c.org/ns/Examples"
     xmlns:ead="http://ead3.archivists.org/schema/"
     xmlns:oai_dc="http://www.openarchives.org/OAI/2.0/oai_dc/"
     xmlns:dc="http://purl.org/dc/elements/1.1/"
     xmlns:xi="http://www.w3.org/2001/XInclude"
     xml:lang="eng"
     xml:id="attr-scriptcode"
     type="attributeDocumentation">
   <head>
      <att>scriptcode</att>
      <seg type="fullName">Script Code</seg>
   </head>
   <div type="summary">
      <p>The code for the writing script used with a given language. Content should
                        be taken from ISO 15924 Codse for the Representation of Names of Scripts, or
                        another controlled list, as specified in the <att>scriptencoding</att>
                        attribute in <gi>control</gi>. Available in <gi>script</gi>.</p>
   </div>
   <div type="dataType">
      <p>NMTOKEN</p>
   </div>
</div>
